[
  {
    "local": "CCBB BH",
    "horario": "16h",
    "endereco": "Praça da Liberdade, 450 - Funcionários",
    "preco": "Gratuito – retirada online",
    "data": "2024-06-14"
  },
  {
    "local": "CEDIN - Centro de Estudos em Direito e Negócios",
    "horario": "18h",
    "endereco": "Rua Paraíba, 1170 Savassi",
    "preco": "Gratuito – retirada online",
    "data": "2024-06-14"
  },
  {
    "local": "Rua Manoelina Dornelas Bairro",
    "horario": "18h",
    "endereco": "Rua Manoelina Dornelas Bairro – Bairro Jaqueline",
    "preco": "Gratuito",
    "data": "2024-06-14"
  },
  {
    "local": "Distrital",
    "horario": "20h",
    "endereco": "Rua Opala, s/n – Cruzeiro",
    "preco": "R$20 – disponível online",
    "data": "2024-06-14"
  },
  {
    "local": "Lab.",
    "horario": "22h",
    "endereco": "Av. do Contorno, 6342 Savassi",
    "preco": "R$25 – disponível online",
    "data": "2024-06-14"
  },
  {
    "local": "Colégio Arnaldo - Unidade Anchieta",
    "horario": "9h",
    "endereco": "Rua Dom Vital, 80 – Anchieta",
    "preco": "a partir de R$8 – disponível online",
    "data": "2024-06-15"
  },
  {
    "local": "Colégio Arnaldo - Unidade Funcionários",
    "horario": "9h",
    "endereco": "Rua dos Timbiras, 540 Funcionários",
    "preco": "a partir de R$8 – disponível online",
    "data": "2024-06-15"
  },
  {
    "local": "Rua José Dias Viêira",
    "horario": "9h",
    "endereco": "Rua José Dias Viêira, 46, Entrada pela Rua Feliciano Ribeiro – Venda Nova",
    "preco": "Gratuito - Retirada online",
    "data": "2024-06-15"
  },
  {
    "local": "Centro Acadêmico de Esporte e Lazer",
    "horario": "10h",
    "endereco": "Rua Dom José Gaspar, 290 – Coração Eucarístico",
    "preco": "R$20 – disponível online",
    "data": "2024-06-15"
  },
  {
    "local": "Museu dos Brinquedos",
    "horario": "10h ás 12h30 e 14h às 17h",
    "endereco": "Av. Afonso Pena, 2564 – Funcionários",
    "preco": "R$15 (meia-entrada) | R$30 (inteira)",
    "data": "2024-06-15"
  },
  {
    "local": "Escola da Serra",
    "horario": "10h30",
    "endereco": "Rua do Ouro, 1900",
    "preco": "R$17,50 – disponível online",
    "data": "2024-06-15"
  },
  {
    "local": "CCBB BH",
    "horario": "11h",
    "endereco": "Praça da Liberdade, 450 - Funcionários",
    "preco": "Gratuito – retirada online",
    "data": "2024-06-15"
  },
  {
    "local": "Colégio Domínio",
    "horario": "12h",
    "endereco": "Rua Nayda Salles Teixeira, 37 – Camargos",
    "preco": "R$10 – disponível online",
    "data": "2024-06-15"
  },
  {
    "local": "Mamute Bar",
    "horario": "12h",
    "endereco": "Rua Brás Cubas, 118 – Anchieta",
    "preco": "R$12 – disponível online",
    "data": "2024-06-15"
  },
  {
    "local": "Nossa Escola Sistema de Educação",
    "horario": "14h",
    "endereco": "Rua Padre Rolim, 959 – Funcionários",
    "preco": "R$20 – disponível online",
    "data": "2024-06-15"
  },
  {
    "local": "Mandaknega",
    "horario": "15h",
    "endereco": "Rua Lignito, 22 – Santa Efigênia",
    "preco": "R$5",
    "data": "2024-06-15"
  },
  {
    "local": "Paróquia Nossa Senhora do Carmo – Sion",
    "horario": "16h",
    "endereco": "Rua Grão Mogol, 502 – Carmo",
    "preco": "Gratuito",
    "data": "2024-06-15"
  },
  {
    "local": "Colégio Escolápio São Miguel",
    "horario": "16h",
    "endereco": "Rua Ildefonso Alvin, 501 – Nova Floresta",
    "preco": "R$10 – disponível online",
    "data": "2024-06-15"
  },
  {
    "local": "Comunidade Católica Reviver",
    "horario": "18h",
    "endereco": "Rua Tabaiares, 30 – Floresta",
    "preco": "R$ 25,00 (incluso comida e bebida)",
    "data": "2024-06-15"
  },
  {
    "local": "Paróquia São Gabriel",
    "horario": "18h",
    "endereco": "Rua Theodoro Bonfim, 85",
    "preco": "Gratuito",
    "data": "2024-06-15"
  },
  {
    "local": "Labareda Clube",
    "horario": "19h",
    "endereco": "Av. Portugal, 4020 – Itapoã",
    "preco": "R$40 – disponível online",
    "data": "2024-06-15"
  },
  {
    "local": "Granada Iate Clube",
    "horario": "19h",
    "endereco": "Rua Istambul, 345 – Braúnas",
    "preco": "R$30 – disponível online",
    "data": "2024-06-15"
  },
  {
    "local": "Comunidade Nossa Senhora das Graças – Paróquia Jesus Ressuscitado",
    "horario": "20h",
    "endereco": "R. Dr. Geraldo Starling Soares, 460 – Regina",
    "preco": "Gratuito",
    "data": "2024-06-15"
  },
  {
    "local": "Quintal da Casa",
    "horario": "21h",
    "endereco": "Rua Padre Marinho 30 – Santa Efigênia",
    "preco": "R$20 – disponível online",
    "data": "2024-06-15"
  },
  {
    "local": "Gruta!",
    "horario": "22h",
    "endereco": "Rua Pitangui, 3613 – Horto",
    "preco": "R$20 – disponível online",
    "data": "2024-06-15"
  },  
  {
    "local": "ARRAIALTO!",
    "horario": "22h",
    "endereco": "Espaço Meet – Av. Raja Gabáglia 2671 – São Bento",
    "preco": "R$25 – disponível online",
    "data": "2024-06-15"
  },
  {
    "local": "Movimento Sinergia – 6ª Edição – Arraiá Junino",
    "horario": "9h",
    "endereco": "Parque Eco. Prof. Marcos Mazzoni – Rua Professor Costa Chiabi em frente ao nº 333 – Cidade Nova",
    "preco": "Gratuito",
    "data": "2024-06-16"
  },
  {
    "local": "Arraial do CCBB BH",
    "horario": "11h",
    "endereco": "CCBB BH – Praça da Liberdade",
    "preco": "Gratuito – retirada online",
    "data": "2024-06-16"
  },
  {
    "local": "Tropeirão Junino do EJC",
    "horario": "11h",
    "endereco": "Paróquia Nossa Senhora de Nazaré – Rua Carmésia, 540 – Santa Inês",
    "preco": "R$20",
    "data": "2024-06-16"
  },
  {
    "local": "Arraiá da Nossa Senhora Rainha",
    "horario": "12h",
    "endereco": "Paróquia Nossa Senhora Rainha – Rua Modesto Carvalho de Araújo, 227 – Belvedere",
    "preco": "Gratuito",
    "data": "2024-06-16"
  },
  {
    "local": "Arraiá das Piranhas",
    "horario": "14h",
    "endereco": "O Quinteiro Bar – Rua Salinas, 1008 Santa Tereza",
    "preco": "R$25 – disponível online",
    "data": "2024-06-16"
  },
  {
    "local": "Arraiá Kids",
    "horario": "15h",
    "endereco": "Shopping Estação – Av. Cristiano Machado, 11833 – Vila Cloris",
    "preco": "Gratuito – retirada de ingressos antecipada",
    "data": "2024-06-16"
  },
  {
    "local": "Arraiá da 5 de janeiro",
    "horario": "15h",
    "endereco": "Rua 5 de janeiro – Bairro Mariano de Abreu",
    "preco": "Gratuito",
    "data": "2024-06-16"
  },
  {
    "local": "Arraiá do Ao vivão",
    "horario": "15h",
    "endereco": "Bar da Orla – Av. Otacílio Negrão de Lima, 2640 – São Luiz",
    "preco": "Gratuito – retire seu ingresso",
    "data": "2024-06-16"
  },
  {
    "local": "Arraiá Intrépida Alegria – 3ª Edição",
    "horario": "16h",
    "endereco": "Intrépida Alegria – Rua Alfredo Guzella, 123 – Planalto",
    "preco": "R$25 – disponível online",
    "data": "2024-06-16"
  },
  {
    "local": "4.º Arraiá da Suvaco Xerôso",
    "horario": "16h",
    "endereco": "Galpão54 – Rua Francisco Soucasseaux, 54 – Lagoinha",
    "preco": "R$17,50 – disponível online",
    "data": "2024-06-16"
  },
  {
    "local": "Arraiá do Raiz com Chama Chuva",
    "horario": "18h",
    "endereco": "Forró Raiz – Av. Raja Gabáglia, 4678 – Santa Lúcia",
    "preco": "R$30 – disponível online",
    "data": "2024-06-16"
  },
  {
    "local": "Arraiá da Autêntica",
    "horario": "19h",
    "endereco": "Autêntica – Rua Álvares Maciel, 312 – Santa Efigênia",
    "preco": "R$25 – disponível online",
    "data": "2024-06-16"
  },
  {
    "local": "Arraiá PUC MINAS",
    "horario": "8h30 às 21h",
    "endereco": "PUC Minas São Gabriel – Rua Edson Silveira, 130 – São Gabriel (Estacionamento em frente ao bloco H)",
    "preco": "Gratuito",
    "data": "2024-06-18"
  },
  {
    "local": "Arraiá da Vovó Luiza",
    "horario": "10h ás 12h30 e 14h às 17h",
    "endereco": "Museu dos Brinquedos – Av. Afonso Pena, 2564 – Funcionários",
    "preco": "R$15 (meia-entrada) | R$30 (inteira)",
    "data": "2024-06-22"
  },
  {
    "local": "5º Arraiá do Rock no São Bento",
    "horario": "11h",
    "endereco": "Avenida Bento Simão, 100 – São Bento",
    "preco": "Gratuito – retire seu ingresso",
    "data": "2024-06-22"
  },
  {
    "local": "II ArraiAU da Pedigri",
    "horario": "12h",
    "endereco": "Underground Black Pub – Av. Itaú, 540A – Jardim São José",
    "preco": "R$10 – disponível online",
    "data": "2024-06-22"
  },
  {
    "local": "JURISDIÇÃO CAIPIRA – a festa junina do direito UFMG",
    "horario": "15h",
    "endereco": "Faculdade de Direito da UFMG – Avenida João Pinheiro, 100 Centro",
    "preco": "R$25 – disponível online",
    "data": "2024-06-22"
  },
  {
    "local": "Arraiá Intrépida Alegria – 3ª Edição",
    "horario": "16h",
    "endereco": "Intrépida Alegria – Rua Alfredo Guzella, 123 – Planalto",
    "preco": "R$25 – disponível online",
    "data": "2024-06-22"
  },
  {
    "local": "Arraiá da Amadoria – Festa Junina com É o Amô e Projeto Forrozim",
    "horario": "16h",
    "endereco": "Amadoria – Rua Mucuri, 325 – Floresta",
    "preco": "R$40 – disponível online",
    "data": "2024-06-22"
  },
  {
    "local": "Minas Rock Beer – Edição Festa Junina",
    "horario": "16h",
    "endereco": "Av. Sinfrônio Brochado, 1053 – Barreiro",
    "preco": "R$20 – disponível online",
    "data": "2024-06-22"
  },
  {
    "local": "Arraiá EJC Santê",
    "horario": "18h",
    "endereco": "Praça Duque de Caxias – Santa Tereza",
    "preco": "Gratuito",
    "data": "2024-06-22"
  },
  {
    "local": "Arraiá da Faculdade Arnaldo",
    "horario": "18h",
    "endereco": "Faculdade Arnaldo – Campus Pilar – Rua Professor Otílio Macedo, 12 – Pilar",
    "preco": "R$15 – disponível online",
    "data": "2024-06-22"
  },
  {
    "local": "ARRAIÁ MAMÃE BARREIRO – Banda Pedro Paulo e Cristina",
    "horario": "19h",
    "endereco": "Allegretto – Rua Antônio Teresino, 12 Santa Cruz (Barreiro)",
    "preco": "R$65 – disponível online",
    "data": "2024-06-22"
  },
  {
    "local": "Arraiá do CCPE",
    "horario": "10h",
    "endereco": "Centro Cultural Padre Eustáquio – Rua Jacutinga, 550 – Padre Eustáquio",
    "preco": "Gratuito",
    "data": "2024-06-23"
  },
  {
    "local": "Arraiá Kids",
    "horario": "15h",
    "endereco": "Shopping Estação – Av. Cristiano Machado, 11833 – Vila Cloris",
    "preco": "Gratuito – retirada de ingressos antecipada",
    "data": "2024-06-23"
  },
  {
    "local": "Arraiá Baianeiros: A mistura junina",
    "horario": "14h",
    "endereco": "UniBH – Campus Buritis – Av. Professor Mário Werneck, 1685",
    "preco": "R$20 – disponível online",
    "data": "2024-06-23"
  },
  {
    "local": "Arraiá da Vovó Luiza",
    "horario": "10h às 12h30 e 14h às 17h",
    "endereco": "Museu dos Brinquedos – Av. Afonso Pena, 2564 – Funcionários",
    "preco": "R$15 (meia-entrada) | R$30 (inteira)",
    "data": "2024-06-29"
  },
  {
    "local": "Festa junina CÉIA 2024",
    "horario": "12h",
    "endereco": "R. Ramos de Azevedo, 153 – Monsenhor Messias",
    "preco": "R$16 – disponível online",
    "data": "2024-06-29"
  },
  {
    "local": "Trem Caipira – Apresentação de quadrilha + brincadeiras juninas",
    "horario": "14h",
    "endereco": "Museu de Artes e Ofícios – Praça Rui Barbosa, 600 – Centro",
    "preco": "Gratuito",
    "data": "2024-06-29"
  },
  {
    "local": "Arraiá do São Miguel",
    "horario": "14h",
    "endereco": "Aquilombar Cultura e Diversidade – Rua Itapecerica, 865 – Lagoinha",
    "preco": "R$15 – disponível online",
    "data": "2024-06-29"
  },
  {
    "local": "Arraiá da Leste e Andacunfé – Coco da Gente convida o Bloco de Pífanos + Andacunfé + Trio Bem-te-quero + Forró de Cabo a Rabo",
    "horario": "15h",
    "endereco": "Escadão Agroflorestal – Rua Tulipa, 125 – Bairro Esplanada",
    "preco": "Gratuito",
    "data": "2024-06-29"
  },
  {
    "local": "Forronejo – Banda Bloco Me Deixe + Forró dos Menino",
    "horario": "17h",
    "endereco": "Cervejaria Rhara – Rua Cristina, 1203 – São Pedro",
    "preco": "R$25 – disponível online",
    "data": "2024-06-29"
  },
  {
    "local": "Festa Junina da Umbigo",
    "horario": "18h",
    "endereco": "Casa Umbigo – Rua Hermílio Alves, 437 – Santa Tereza",
    "preco": "R$42 – disponível online",
    "data": "2024-06-29"
  },
  {
    "local": "Arraiá de Santa Efigênia",
    "horario": "19h",
    "endereco": "Paróquia Santa Efigênia dos Militares – Rua Álvares Maciel, 223, Santa Efigênia",
    "preco": "Gratuito",
    "data": "2024-06-29"
  },
  {
    "local": "Festa Junina do Xita",
    "horario": "20h",
    "endereco": "Av. Mem de Sá, 1205 – Santa Efigênia",
    "preco": "R$15 – disponível online",
    "data": "2024-06-29"
  },
  {
    "local": "Arraiá na Floresta – Percussão Circular",
    "horario": "13h",
    "endereco": "Av. Assis Chateaubriand, 514 – Floresta",
    "preco": "Gratuito",
    "data": "2024-06-30"
  },
  {
    "local": "Arraiá Kids",
    "horario": "16h",
    "endereco": "Shopping Estação – Av. Cristiano Machado, 11833 – Vila Cloris",
    "preco": "Gratuito – retirada de ingressos antecipada",
    "data": "2024-06-30"
  },
  {
    "local": "Arraiá da Inclusão",
    "horario": "13h30",
    "endereco": "APAE BH – Rua Cristal, 78 – Santa Tereza",
    "preco": "Gratuito – retire seu ingresso",
    "data": "2024-07-06"
  },
  {
    "local": "Arraiá do Beiço – Beiço do Wando + Pelasamba + Pé de Serra",
    "horario": "14h",
    "endereco": "Av. Brasil, 10 – Santa Efigênia",
    "preco": "Gratuito – retire seu ingresso",
    "data": "2024-07-06"
  },
  {
    "local": "Arraiá do Roça Bar",
    "horario": "17h",
    "endereco": "Roça Bar Pizzaria – Av. Maurete José dos Santos, 310 – Manacás",
    "preco": "Gratuito – retire seu ingresso",
    "data": "2024-07-06"
  },
  {
    "local": "Julina do Quintal",
    "horario": "12h",
    "endereco": "Quintal do Chalé – Av. Professor Mário Werneck, 530 – Estoril",
    "preco": "R$35 – disponível online",
    "data": "2024-07-13"
  },
  {
    "local": "Arraiá Nossa Senhora das Dores",
    "horario": "17h",
    "endereco": "Paróquia Nossa Senhora das Dores – Rua Silva Jardim, 100, Floresta",
    "preco": "Gratuito",
    "data": "2024-07-13"
  },
  {
    "local": "Arraiá do Cruzeiro 2024 – Trio Forrozão",
    "horario": "15h",
    "endereco": "Cruzeiro Esporte Clube – Rua dos Guajajaras, 1722 Barro Preto",
    "preco": "R$40 – disponível online",
    "data": "2024-07-20"
  }
]